Metadata-Version: 2.2
Name: dataframe_with_buttons
Version: 0.0.3.0
Summary: Display Dataframe with buttons
Home-page: 
Author: Rishabh Jain
Author-email: rishabh_jain@hakkoda.io
Requires-Python: >=3.7
License-File: LICENSE
Requires-Dist: streamlit>=0.63
Requires-Dist: pandas
Provides-Extra: devel
Requires-Dist: wheel; extra == "devel"
Requires-Dist: pytest==7.4.0; extra == "devel"
Requires-Dist: playwright==1.48.0; extra == "devel"
Requires-Dist: requests==2.31.0; extra == "devel"
Requires-Dist: pytest-playwright-snapshot==1.0; extra == "devel"
Requires-Dist: pytest-rerunfailures==12.0; extra == "devel"
Dynamic: author
Dynamic: author-email
Dynamic: description
Dynamic: description-content-type
Dynamic: provides-extra
Dynamic: requires-dist
Dynamic: requires-python
Dynamic: summary
